LICENSE.txt
MANIFEST.in
README.rst
setup.cfg
setup.py
CoPipes.egg-info/PKG-INFO
CoPipes.egg-info/SOURCES.txt
CoPipes.egg-info/dependency_links.txt
CoPipes.egg-info/top_level.txt
CoPipes.egg-info/zip-safe
copipes/__init__.py
copipes/example.py
copipes/test.py